webexpythonsdk_async/__init__.py
webexpythonsdk_async/_metadata.py
webexpythonsdk_async/config.py
webexpythonsdk_async/environment.py
webexpythonsdk_async/exceptions.py
webexpythonsdk_async/generator_containers.py
webexpythonsdk_async/response_codes.py
webexpythonsdk_async/restsession.py
webexpythonsdk_async/utils.py
webexpythonsdk_async/api/__init__.py
webexpythonsdk_async/api/access_tokens.py
webexpythonsdk_async/api/admin_audit_events.py
webexpythonsdk_async/api/attachment_actions.py
webexpythonsdk_async/api/events.py
webexpythonsdk_async/api/guest_issuer.py
webexpythonsdk_async/api/licenses.py
webexpythonsdk_async/api/meeting_invitees.py
webexpythonsdk_async/api/meeting_registrants.py
webexpythonsdk_async/api/meeting_templates.py
webexpythonsdk_async/api/meetings.py
webexpythonsdk_async/api/memberships.py
webexpythonsdk_async/api/messages.py
webexpythonsdk_async/api/organizations.py
webexpythonsdk_async/api/people.py
webexpythonsdk_async/api/recordings.py
webexpythonsdk_async/api/roles.py
webexpythonsdk_async/api/room_tabs.py
webexpythonsdk_async/api/rooms.py
webexpythonsdk_async/api/team_memberships.py
webexpythonsdk_async/api/teams.py
webexpythonsdk_async/api/webhooks.py
webexpythonsdk_async/models/__init__.py
webexpythonsdk_async/models/dictionary.py
webexpythonsdk_async/models/immutable.py
webexpythonsdk_async/models/simple.py
webexpythonsdk_async/models/cards/__init__.py
webexpythonsdk_async/models/cards/actions.py
webexpythonsdk_async/models/cards/adaptive_card_component.py
webexpythonsdk_async/models/cards/card_elements.py
webexpythonsdk_async/models/cards/cards.py
webexpythonsdk_async/models/cards/containers.py
webexpythonsdk_async/models/cards/inputs.py
webexpythonsdk_async/models/cards/options.py
webexpythonsdk_async/models/cards/types.py
webexpythonsdk_async/models/cards/utils.py
webexpythonsdk_async/models/mixins/__init__.py
webexpythonsdk_async/models/mixins/access_token.py
webexpythonsdk_async/models/mixins/admin_audit_event.py
webexpythonsdk_async-0.1.3.dist-info/licenses/LICENSE
webexpythonsdk_async-0.1.3.dist-info/METADATA
webexpythonsdk_async-0.1.3.dist-info/WHEEL
webexpythonsdk_async-0.1.3.dist-info/top_level.txt
webexpythonsdk_async-0.1.3.dist-info/RECORD
