Metadata-Version: 2.4
Name: webexpythonsdk_async
Version: 0.1.3
Summary: An async Webex SDK for Python using httpx and JWT.
Author-email: Rainux He <rainuxhe@outlook.com>
Project-URL: Homepage, https://github.com/rainuxhe/WebexPythonSDK-async
Project-URL: Documentation, https://github.com/rainuxhe/WebexPythonSDK-async#readme
Project-URL: Repository, https://github.com/rainuxhe/WebexPythonSDK-async.git
Classifier: Programming Language :: Python :: 3
Classifier: Programming Language :: Python :: 3.11
Classifier: License :: OSI Approved :: MIT License
Classifier: Operating System :: OS Independent
Classifier: Development Status :: 4 - Beta
Classifier: Intended Audience :: Developers
Classifier: Topic :: Software Development :: Libraries
Requires-Python: >=3.11
License-File: LICENSE
Requires-Dist: httpx>=0.23.0
Requires-Dist: pyjwt>=2.4.0
Dynamic: license-file
